setup.py
x256/__init__.py
x256/x256.py
x256.egg-info/PKG-INFO
x256.egg-info/SOURCES.txt
x256.egg-info/dependency_links.txt
x256.egg-info/top_level.txt