Metadata-Version: 1.1
Name: x256
Version: 0.0.3
Summary: x256: manipulate xterm 256 color codes
Home-page: https://github.com/magarcia/python-x256
Author: Martin Garcia
Author-email: newluxfero@gmail.com
License: MIT
Platform: POSIX
Classifier: Development Status :: 4 - Beta
Classifier: Environment :: Console
Classifier: Intended Audience :: Developers
Classifier: License :: OSI Approved :: MIT License
Classifier: Programming Language :: Python :: 2.5
Classifier: Programming Language :: Python :: 2.6
Classifier: Programming Language :: Python :: 2.7
Classifier: Programming Language :: Python :: 3
Classifier: Operating System :: OS Independent
Classifier: Topic :: Utilities
